buildable/__about__.py
buildable/__init__.py
buildable/base.py
buildable/live_set.py
buildable/py.typed
buildable/util.py
buildable-0.4.0.dist-info/METADATA
buildable-0.4.0.dist-info/WHEEL
buildable-0.4.0.dist-info/licenses/LICENSE.txt
buildable-0.4.0.dist-info/RECORD
