Metadata-Version: 2.3
Name: buildable
Version: 0.4.0
Summary: Combine and edit Ableton Live sets (.als files).
Project-URL: Documentation, https://github.com/kmontag/buildable#readme
Project-URL: Issues, https://github.com/kmontag/buildable/issues
Project-URL: Source, https://github.com/kmontag/buildable
Author-email: Kevin Montag <kmontag@cs.stanford.edu>
License-Expression: MIT
License-File: LICENSE.txt
Keywords: ableton,live
Classifier: Development Status :: 3 - Alpha
Classifier: Programming Language :: Python
Classifier: Programming Language :: Python :: 3.8
Classifier: Programming Language :: Python :: 3.9
Classifier: Programming Language :: Python :: 3.10
Classifier: Programming Language :: Python :: 3.11
Classifier: Programming Language :: Python :: 3.12
Classifier: Programming Language :: Python :: Implementation :: CPython
Classifier: Programming Language :: Python :: Implementation :: PyPy
Requires-Python: >=3.8
Requires-Dist: lxml~=5.2.2
